used_addr_check/__init__.py
used_addr_check/__main__.py
used_addr_check/cli.py
used_addr_check/download_list.py
used_addr_check/index_create.py
used_addr_check/index_search.py
used_addr_check/scan_file.py
used_addr_check-0.2.0.dist-info/METADATA
used_addr_check-0.2.0.dist-info/WHEEL
used_addr_check-0.2.0.dist-info/entry_points.txt
used_addr_check-0.2.0.dist-info/licenses/LICENSE
used_addr_check-0.2.0.dist-info/RECORD
