Metadata-Version: 2.4
Name: used_addr_check
Version: 0.2.0
Summary: A tool to efficiently check if a Bitcoin Address has ever been used before
Project-URL: Homepage, https://github.com/RecRanger/used-addr-check
Project-URL: Issues, https://github.com/RecRanger/used-addr-check/issues
Author-email: RecRanger <RecRanger+package@proton.me>
License-File: LICENSE
Classifier: Operating System :: OS Independent
Classifier: Programming Language :: Python :: 3
Requires-Python: >=3.10
Requires-Dist: backoff>=2.2.1
Requires-Dist: loguru>=0.7.2
Requires-Dist: orjson>=3.10.1
Requires-Dist: polars>=1.37
Requires-Dist: requests>=2.31.0
Requires-Dist: ripgrepy>=2.0.0
Requires-Dist: tqdm>=4.66.2
